README.txt
setup.cfg
setup.py
collective/__init__.py
collective.tipsy.egg-info/PKG-INFO
collective.tipsy.egg-info/SOURCES.txt
collective.tipsy.egg-info/dependency_links.txt
collective.tipsy.egg-info/entry_points.txt
collective.tipsy.egg-info/namespace_packages.txt
collective.tipsy.egg-info/not-zip-safe
collective.tipsy.egg-info/paster_plugins.txt
collective.tipsy.egg-info/requires.txt
collective.tipsy.egg-info/top_level.txt
collective/tipsy/__init__.py
collective/tipsy/configure.zcml
collective/tipsy/tests.py
collective/tipsy/browser/__init__.py
collective/tipsy/browser/configure.zcml
collective/tipsy/browser/tipsy-1.0.0a/LICENSE
collective/tipsy/browser/tipsy-1.0.0a/README
collective/tipsy/browser/tipsy-1.0.0a/Rakefile
collective/tipsy/browser/tipsy-1.0.0a/docs/.gitignore
collective/tipsy/browser/tipsy-1.0.0a/docs/src/index.html.erb
collective/tipsy/browser/tipsy-1.0.0a/docs/src/project.yml
collective/tipsy/browser/tipsy-1.0.0a/docs/src/tipsy-docs.css
collective/tipsy/browser/tipsy-1.0.0a/docs/src/images/tipsy.gif
collective/tipsy/browser/tipsy-1.0.0a/docs/src/javascripts/jquery.tipsy.js
collective/tipsy/browser/tipsy-1.0.0a/docs/src/javascripts/jquery.tipsy.plone.js
collective/tipsy/browser/tipsy-1.0.0a/docs/src/stylesheets/tipsy.css
collective/tipsy/browser/tipsy-1.0.0a/docs/src/stylesheets/tipsy.plone.css
collective/tipsy/browser/tipsy-1.0.0a/src/images/tipsy.gif
collective/tipsy/browser/tipsy-1.0.0a/src/javascripts/jquery.tipsy.js
collective/tipsy/browser/tipsy-1.0.0a/src/javascripts/jquery.tipsy.plone.js
collective/tipsy/browser/tipsy-1.0.0a/src/stylesheets/tipsy.css
collective/tipsy/browser/tipsy-1.0.0a/src/stylesheets/tipsy.plone.css
collective/tipsy/profiles/default/cssregistry.xml
collective/tipsy/profiles/default/jsregistry.xml
collective/tipsy/profiles/default/metadata.xml
docs/HISTORY.txt
docs/INSTALL.txt
docs/LICENSE.GPL
docs/LICENSE.txt