Metadata-Version: 1.0
Name: collective.tipsy
Version: 1.0.0a
Summary: Tipsy for Plone
Home-page: http://svn.plone.org/svn/collective/collective.tipsy/
Author: Quadra Informatique
Author-email: plone@quadra-informatique.fr
License: GPL
Keywords: plone jquery tipsy
Platform: UNKNOWN
Classifier: Framework :: Plone
Classifier: Programming Language :: Python
